LICENSE
README.md
setup.py
culof/__init__.py
culof.egg-info/PKG-INFO
culof.egg-info/SOURCES.txt
culof.egg-info/dependency_links.txt
culof.egg-info/requires.txt
culof.egg-info/top_level.txt
culof/tests/__init__.py
culof/tests/test_cuda_lof.py
culof/tests/test_edge_cases.py
culof/tests/test_numerical_accuracy.py
culof/tests/test_sklearn_comparison.py
python/__init__.py
python/example.py
python/tests/__init__.py
python/tests/test_cuda_lof.py
python/tests/test_edge_cases.py
python/tests/test_numerical_accuracy.py
python/tests/test_sklearn_comparison.py
tests/test_consistency.py