Metadata-Version: 2.2
Name: culof
Version: 0.1.0
Summary: CUDA-accelerated Local Outlier Factor implementation
Home-page: https://github.com/Aminsed/cuLOF
Author: Amin Sedaghat
Author-email: amin32846@gmail.com
Project-URL: Bug Tracker, https://github.com/Aminsed/cuLOF/issues
Project-URL: Documentation, https://github.com/Aminsed/cuLOF
Project-URL: Source Code, https://github.com/Aminsed/cuLOF
Keywords: anomaly detection,outlier detection,cuda,gpu,lof,local outlier factor
Classifier: Development Status :: 3 - Alpha
Classifier: Intended Audience :: Science/Research
Classifier: License :: OSI Approved :: MIT License
Classifier: Programming Language :: Python :: 3
Classifier: Programming Language :: Python :: 3.6
Classifier: Programming Language :: Python :: 3.7
Classifier: Programming Language :: Python :: 3.8
Classifier: Programming Language :: Python :: 3.9
Classifier: Programming Language :: Python :: 3.10
Classifier: Programming Language :: Python :: 3.11
Classifier: Programming Language :: C++
Classifier: Operating System :: POSIX :: Linux
Classifier: Operating System :: Microsoft :: Windows
Classifier: Environment :: GPU :: NVIDIA CUDA
Classifier: Topic :: Scientific/Engineering
Classifier: Topic :: Scientific/Engineering :: Artificial Intelligence
Requires-Python: >=3.6
License-File: LICENSE
Requires-Dist: numpy>=1.15.0
Requires-Dist: matplotlib>=3.0.0
Requires-Dist: scikit-learn>=0.22.0
Dynamic: author
Dynamic: author-email
Dynamic: classifier
Dynamic: description
Dynamic: description-content-type
Dynamic: home-page
Dynamic: keywords
Dynamic: project-url
Dynamic: requires-dist
Dynamic: requires-python
Dynamic: summary
